dotfiles/__init__.py
dotfiles/cli.py
dotfiles/config_manager.py
dotfiles/helpers.py
dotfiles/package_manager.py
dotfiles/commands/__init__.py
dotfiles/commands/backup.py
dotfiles/commands/config.py
dotfiles/commands/install.py
dotfiles/commands/update.py
dotfiles/commands/verify.py
dfiles-0.1.0.dist-info/METADATA
dfiles-0.1.0.dist-info/WHEEL
dfiles-0.1.0.dist-info/entry_points.txt
dfiles-0.1.0.dist-info/licenses/LICENSE
dfiles-0.1.0.dist-info/RECORD
