Metadata-Version: 2.4
Name: dfiles
Version: 0.1.0
Summary: Cross-platform dotfiles automation with Python
Project-URL: Homepage, https://github.com/carlosferreyra/dotfiles
Project-URL: Issues, https://github.com/carlosferreyra/dotfiles/issues
Project-URL: Repository, https://github.com/carlosferreyra/dotfiles.git
Author-email: Carlos Ferreyra <carlosferreyra@example.com>
License: MIT
License-File: LICENSE
Keywords: automation,configuration,dotfiles
Classifier: Development Status :: 3 - Alpha
Classifier: Intended Audience :: Developers
Classifier: License :: OSI Approved :: MIT License
Classifier: Operating System :: OS Independent
Classifier: Programming Language :: Python :: 3
Classifier: Programming Language :: Python :: 3.12
Classifier: Programming Language :: Python :: 3.13
Requires-Python: >=3.12
Requires-Dist: rich>=13.0.0
Requires-Dist: typer>=0.9.0
